Metadata-Version: 2.4
Name: lockersm
Version: 1.0.6b1
Summary: Locker Secret Python SDK
Home-page: https://locker.io
Download-URL: 
Author: CyStack
Author-email: contact@locker.io
Keywords: django,vault management,security
Classifier: Intended Audience :: Developers
Classifier: Operating System :: OS Independent
Classifier: Programming Language :: Python
Classifier: Programming Language :: Python :: 3
Classifier: Programming Language :: Python :: 3 :: Only
Classifier: Programming Language :: Python :: 3.14
Classifier: Programming Language :: Python :: 3.13
Classifier: Programming Language :: Python :: 3.12
Classifier: Programming Language :: Python :: 3.11
Classifier: Programming Language :: Python :: 3.10
Classifier: Programming Language :: Python :: 3.9
Classifier: Programming Language :: Python :: 3.8
Classifier: Topic :: Software Development :: Libraries :: Application Frameworks
Classifier: Topic :: Software Development :: Libraries :: Python Modules
Classifier: Development Status :: 3 - Alpha
Requires-Python: >=3.8
Requires-Dist: six>=1.15.0
Requires-Dist: urllib3>=2.6.3
Requires-Dist: requests>=2.20.0
Dynamic: author
Dynamic: author-email
Dynamic: classifier
Dynamic: description
Dynamic: description-content-type
Dynamic: home-page
Dynamic: keywords
Dynamic: requires-dist
Dynamic: requires-python
Dynamic: summary
